<?xml version='1.0' encoding='UTF-8'?>
<?xml-stylesheet type='text/xsl' href='file:///D:/hetanjin/professionalSoftware/Mesmer/Mesmer-3.0/mesmer2.xsl' media='other'?>
<?xml-stylesheet type='text/xsl' href='file:///D:/hetanjin/professionalSoftware/Mesmer/Mesmer-3.0/mesmer1.xsl' media='screen'?>
<me:mesmer xmlns:me="http://www.chem.leeds.ac.uk/mesmer" xmlns:xsi="http://www.w3.org/2001/XMLSchema-instance" xmlns="http://www.xml-cml.org/schema">
  <moleculeList>
    <molecule id="RO2" description="C3H7O2 C3H7O2_61_b3631gd">
      <atomArray>
        <atom id="C1" elementType="C" x3="-1.91251" y3="-0.706941" z3="0.141897"/>
        <atom id="H2" elementType="H" x3="-1.364177" y3="-1.57081" z3="-0.246643"/>
        <atom id="H3" elementType="H" x3="-2.930845" y3="-0.74428" z3="-0.25895"/>
        <atom id="H4" elementType="H" x3="-1.976923" y3="-0.812414" z3="1.231621"/>
        <atom id="C5" elementType="C" x3="-1.22189" y3="0.60519" z3="-0.245732"/>
        <atom id="H6" elementType="H" x3="-1.202786" y3="0.717527" z3="-1.33715"/>
        <atom id="H7" elementType="H" x3="-1.788028" y3="1.461191" z3="0.144328"/>
        <atom id="C8" elementType="C" x3="0.19903" y3="0.725596" z3="0.282605"/>
        <atom id="H9" elementType="H" x3="0.656561" y3="1.689998" z3="0.040224"/>
        <atom id="H10" elementType="H" x3="0.2637" y3="0.55801" z3="1.362582"/>
        <atom id="O11" elementType="O" x3="1.005791" y3="-0.307666" z3="-0.363931"/>
        <atom id="O12" elementType="O" x3="2.23855" y3="-0.322621" z3="0.112853"/>
      </atomArray>
      <bondArray>
        <bond id="b1" atomRefs2="C1 H2" order="1.0"/>
        <bond id="b2" atomRefs2="C1 H3" order="1.0"/>
        <bond id="b3" atomRefs2="C1 H4" order="1.0"/>
        <bond id="b4" atomRefs2="C1 C5" order="1.0"/>
        <bond id="b5" atomRefs2="C5 H6" order="1.0"/>
        <bond id="b6" atomRefs2="C5 H7" order="1.0"/>
        <bond id="b7" atomRefs2="C5 C8" order="1.0"/>
        <bond id="b8" atomRefs2="C8 H9" order="1.0"/>
        <bond id="b9" atomRefs2="C8 H10" order="1.0"/>
        <bond id="b10" atomRefs2="C8 O11" order="1.0"/>
        <bond id="b11" atomRefs2="O11 O12" order="1.0"/>
      </bondArray>
      <propertyList>
        <property dictRef="me:ZPE">
          <scalar units="kcal/mol">-168642.018574</scalar>
        </property>
        <property dictRef="me:rotConsts">
          <array units="cm-1">0.432870129108 0.0901323541635 0.0815130579436 </array>
        </property>
        <property dictRef="me:symmetryNumber">
          <scalar>1</scalar>
        </property>
        <property dictRef="me:frequenciesScaleFactor">
          <scalar>1.0</scalar>
        </property>
        <!--<property dictRef="me:vibFreqs">
  <array units="cm-1">60.5899 135.4639 204.2976 299.1529 380.967 520.9768 756.9252 885.9478 914.3069 932.2531 1068.5708 1132.8357 1167.2642 1211.4911 1257.2224 1318.8038 1387.6276 1412.6705 1445.1135 1507.1053 1516.8365 1531.8894 1538.3624 3049.8252 3054.4555 3071.8035 3085.8044 3119.7773 3129.5057 3135.4676 </array>
</property>
-->
        <property title="Hessian" dictRef="me:hessian">
          <matrix rows="36" matrixType="squareSymmetricLT" units="Hartree/Bohr2">0.5582432 0.03361679 0.5323283 -0.03129802 0.0378087 0.55173072 -0.05063624 -0.00287654 -0.00552298 0.05053621 -0.00324024 -0.07327876 -0.07623723 0.00046057 0.07681382 -0.00681389 -0.07480327 -0.29406298 0.00873915 0.08051 0.31934012 -0.28346131 0.01823877 0.08473116 0.00265988 -0.00023722 -0.00025128 0.30709864 0.0172605 -0.05063166 -0.00713857 0.00984217 -0.00145541 -0.00301073 -0.02176008 0.05163818 0.08584839 -0.00736161 -0.07999465 0.0308427 -0.00102575 -0.00924553 -0.09194598 0.00533364 0.08336903 -0.09776357 -0.10107573 -0.00492327 -0.00088823 0.0005451 2.559e-05 -0.01215789 -0.02879305 -0.00288021 0.10250839 -0.10038957 -0.26213855 -0.01192755 -0.0038608 -0.00798563 -0.00035446 0.00105815 0.00386573 0.0003665 0.1094745 0.28626364 -0.00531838 -0.01245226 -0.0507954 -0.01486843 -0.02925331 0.00057365 0.00453131 0.01117271 -9.651e-05 0.00765964 0.01021221 0.0505909 -0.10922233 0.03625481 -0.03137791 -0.00125357 0.0004174 -0.00138457 -0.01474308 0.02197127 -0.02020353 0.00740027 -0.00909637 0.00902892 0.49191014 0.03472802 -0.13217029 0.04188651 -0.00565628 0.00732219 -0.00462344 0.00014667 -0.00202781 0.00088899 0.01745092 -0.02064385 0.01895079 0.04254932 0.55978743 -0.03123711 0.04249724 -0.11888197 -0.01778371 0.02397933 -0.01689498 0.00567549 -0.00855835 0.00680589 0.00148802 -0.00084672 0.0001998 0.0032257 0.03077829 0.56220498 0.0084963 0.01746736 0.0006528 0.00044333 -0.00078126 0.00035863 0.0007282 -0.00038601 0.00065807 -0.00144727 0.00298437 -0.00262961 -0.10213966 -0.1023349 -0.00247131 0.11458923 -0.00867402 -0.01984389 -0.00035354 -0.00016726 0.00099845 0.00014322 0.00027278 0.00050293 -0.00050953 0.00302599 -0.00149649 0.00285876 -0.10418905 -0.25527767 -0.00559424 0.1118376 0.27748803 0.00865027 0.0181404 0.00042391 0.00082623 -0.00034155 0.0004602 0.00014014 -0.00079526 0.00062989 -0.00218304 0.00300172 -0.00159451 -0.00380006 -0.00619587 -0.05088442 0.00407898 0.00445333 0.05087767 -0.00061469 -0.00541708 -0.01791882 -0.00139635 0.00317669 -0.00193971 0.0003072 -0.0007555 0.00017983 0.0005659 -5.578e-05 0.00082825 -0.04982086 -0.002507 -0.00274862 -0.00015185 -0.0043382 -0.0155139 0.05430028 0.00069953 0.00676036 0.02406251 0.00289525 -0.00281202 0.00290834 -0.00057224 0.00085142 -0.0008638 -0.00074791 0.00099866 -0.00032301 -0.00157298 -0.07221286 -0.07481863 0.00081781 -0.00880745 -0.02840803 -0.00169818 0.07691213 -0.00111769 -0.00444491 -0.01749379 -0.00211523 0.0031015 -0.00044483 -0.0002104 -0.00019001 0.00085194 0.00056454 0.00018411 0.00058912 -0.00205788 -0.07503656 -0.28220835 -0.00041992 -0.00074833 5.036e-05 0.00387195 0.0804327 0.30790357 -0.02306919 0.00703859 0.00224472 0.00090566 -0.00081303 0.00091692 -0.00013913 0.00112557 -0.00182253 0.00195232 -0.00182045 0.00073795 -0.19499717 0.00508012 0.019791 -0.01862234 0.00181872 0.00682432 0.00312134 -0.00154363 -0.00144231 0.56485812 0.02409153 -0.00335585 -0.00756781 -0.00091643 0.0010586 -0.00027086 0.00270487 -0.00307196 0.00326036 0.00116628 0.00028609 -0.00066596 0.00779794 -0.08720803 -0.00050731 -0.03241978 0.00434109 0.01011705 0.011358 -0.00248269 -0.00395554 0.01731534 0.58144157 -0.01909976 -0.00033817 0.00962322 -0.00105102 -0.00041281 -0.00098287 -0.0031198 0.00350439 -0.00300837 0.00024284 -0.00027416 0.00045913 0.02819658 0.00087006 -0.08566913 -0.00123219 0.00045049 -0.00110681 0.03139802 -0.00245929 -0.01157171 0.03482771 -0.08493883 0.42676258 -0.00505689 -0.00123624 0.00371012 0.00019193 -0.00024406 -1.93e-05 -0.00088191 0.00132716 -0.00112871 0.00016965 0.0001496 0.00017769 -0.01385442 0.02063072 -0.01852497 0.0011107 -0.00066817 -0.00049917 0.00111609 1.654e-05 0.00032343 -0.1195673 0.08581231 -0.07856534 0.12595465 0.00109834 0.00093699 -0.00078317 -4.75e-06 -3.553e-05 6.532e-05 0.00029826 2.395e-05 0.00031168 -0.00027587 0.00049708 -0.00016049 -0.00035251 -0.00143033 0.0012679 0.00021554 0.00075766 -0.0004864 0.00037052 -2.129e-05 -0.00019124 0.08687098 -0.16516443 0.10317865 -0.09362397 0.16981922 0.00257645 0.00043002 -0.00053647 0.00023019 -6.951e-05 0.00011838 0.00060626 -0.00052797 0.00041272 -8.315e-05 5.562e-05 -0.00013143 0.00569504 -0.00820818 0.00908151 -0.00052741 0.00026194 9.773e-05 -0.00070972 1.947e-05 0.00069068 -0.07376303 0.09921298 -0.13163064 0.08447676 -0.10317521 0.15511654 0.00201602 -0.00173782 -6.031e-05 -0.00012366 9.16e-05 -0.00013508 0.00048808 0.00023376 0.0001478 -0.00024278 0.00120815 -0.000225 -0.0146238 -0.02721769 0.00168475 -0.00540585 0.001163 0.00214051 0.00083715 0.00036783 0.0001211 -0.11314545 -0.11217329 0.00966396 0.00943241 0.01506608 -0.00131772 0.12025778 0.00042451 0.0012756 -0.00014673 -6e-06 -4.93e-05 3.95e-05 -9.28e-06 0.00018568 -4.787e-05 -0.00057471 0.00027447 -0.00025799 0.00273485 0.00601148 0.00075673 0.00194721 0.00092007 -0.00013921 -0.00084217 0.00010859 0.00040531 -0.1087907 -0.25282219 0.02324448 -0.01039972 -0.01616717 0.00280094 0.12183293 0.27057634 -0.00095105 -0.00048223 -5.613e-05 6.148e-05 -0.00012232 7.772e-05 -8.146e-05 6.239e-05 -0.00013629 6.216e-05 -0.000318 0.00027449 0.00486909 0.01069633 0.0008938 0.00251391 -0.00110921 4.298e-05 -0.000645 -4.077e-05 0.00021369 0.01450014 0.02931893 -0.04977375 0.00968763 0.01642066 0.00131126 -0.01158042 -0.0176969 0.06041672 0.00049227 -0.00011952 -0.00036479 -0.00040931 0.00073449 0.00061934 0.00012061 -8.455e-05 0.00041527 -2.042e-05 0.00020575 4.844e-05 -0.0023338 0.0157338 0.03619799 0.0022166 5.259e-05 -0.00027809 -0.00638061 0.00134194 0.00252258 -0.08145483 -0.01750211 -0.03094723 -0.00128364 -0.00717827 -0.01370361 -0.00227389 -0.0054318 -0.01368247 0.45826865 0.00079031 -7.419e-05 0.0006658 0.0002197 -0.0004635 -0.00080473 -0.00014747 0.0001029 -0.00042508 -0.00020109 7.147e-05 -0.00015205 0.00402201 -0.00177612 -0.00459792 0.00018294 0.0003505 0.0009251 -0.00044657 0.00053641 0.00077875 -0.02976275 -0.06863784 -0.03633601 -0.00205773 0.00985329 0.00854636 0.0002801 -0.01259984 -0.03871659 0.00469053 0.08517474 -0.00096843 0.00069455 0.00072933 0.00026661 0.00013491 0.00048682 -0.00023266 0.00027509 7.237e-05 -1.8e-07 -5.948e-05 -0.00020572 0.01022684 -0.00618635 -0.01535112 -0.0010392 -8.229e-05 0.00111116 0.0002824 -0.00018261 0.00195346 -0.05882391 -0.03923463 -0.12912416 -0.00019239 -0.01741817 -0.03917483 -0.00123313 -0.01126903 -0.01748604 -0.08005356 0.1003383 0.28746343 0.00057644 -0.0001534 0.00012731 -2.966e-05 -0.00011003 -0.0001158 -1.931e-05 1.876e-05 -0.00011109 -7.636e-05 0.00014245 2.924e-05 0.00367828 0.00139631 0.00470276 0.00018261 -0.000134 -0.0003862 -0.00188359 -3.94e-06 -4.015e-05 -0.01984203 0.01276535 0.02968621 0.00266872 -0.00248434 -0.00348006 0.00278399 -0.00088512 -0.00475401 -0.36694164 0.02243002 0.13176762 0.37890254 -0.0004057 0.00019193 -0.00026893 7.038e-05 -0.00011292 0.00020112 6.8e-06 1.605e-05 7.25e-05 5.57e-06 7.38e-06 7.06e-05 -0.00053669 -0.00037416 -0.00435631 0.00046911 6.677e-05 -0.00027129 0.00115529 0.00016873 -0.00033579 0.02348123 -0.00438437 -0.00648881 0.00029356 0.00093055 0.00065352 0.00088535 0.00228627 0.00198771 0.00755714 -0.01253782 -0.0270103 -0.03298206 0.01374161 -0.00027077 0.00031153 -0.0006858 0.000375 -0.00026326 0.00057429 0.00015722 -0.00012732 0.00033951 2.708e-05 -3.979e-05 0.00013648 -0.00241823 -0.00382057 -0.00929602 5.725e-05 0.00022938 -0.00010817 0.00291532 -0.00032687 -0.00053413 0.05600903 -0.00476839 -0.02397749 0.00055426 0.00097046 0.00464453 0.00079355 0.00231076 0.00422155 0.09922612 -0.03022193 -0.09047469 -0.15742584 0.03574599 0.11515996 </matrix>
        </property>
        <property dictRef="me:MW">
          <scalar units="amu">75.087</scalar>
        </property>
        <property dictRef="me:spinMultiplicity">
          <scalar>2</scalar>
        </property>
        <property dictRef="me:epsilon">
          <scalar>500.0</scalar>
        </property>
        <property dictRef="me:sigma">
          <scalar>5.0</scalar>
        </property>
      </propertyList>
      <me:energyTransferModel xsi:type="me:ExponentialDown">
        <deltaEDown units="cm-1">400.0</deltaEDown>
      </me:energyTransferModel>
      <me:tmpnode_DOSCMethod name="ClassicalRotors"/>
    </molecule>
    <molecule id="TS_286" description="C3H7O2 C3H7O2_62_b3631gd_286">
      <atomArray>
        <atom id="C1" elementType="C" x3="-1.760115" y3="-1.079073" z3="0.178217"/>
        <atom id="H2" elementType="H" x3="-0.806275" y3="-1.596877" z3="0.030795"/>
        <atom id="H3" elementType="H" x3="-2.540378" y3="-1.646719" z3="-0.340557"/>
        <atom id="H4" elementType="H" x3="-1.989099" y3="-1.098144" z3="1.25056"/>
        <atom id="C5" elementType="C" x3="-1.683988" y3="0.362584" z3="-0.341617"/>
        <atom id="H6" elementType="H" x3="-1.489892" y3="0.361798" z3="-1.424161"/>
        <atom id="H7" elementType="H" x3="-2.679788" y3="0.834038" z3="-0.234384"/>
        <atom id="C8" elementType="C" x3="-0.660679" y3="1.196537" z3="0.349809"/>
        <atom id="H9" elementType="H" x3="-0.318982" y3="2.131321" z3="-0.083695"/>
        <atom id="H10" elementType="H" x3="-0.387209" y3="0.995776" z3="1.381839"/>
        <atom id="O11" elementType="O" x3="1.738386" y3="-0.097184" z3="-0.522047"/>
        <atom id="O12" elementType="O" x3="2.616653" y3="-0.260502" z3="0.309691"/>
      </atomArray>
      <bondArray>
        <bond id="b1" atomRefs2="C1 H2" order="1.0"/>
        <bond id="b2" atomRefs2="C1 H3" order="1.0"/>
        <bond id="b3" atomRefs2="C1 H4" order="1.0"/>
        <bond id="b4" atomRefs2="C1 C5" order="1.0"/>
        <bond id="b5" atomRefs2="C5 H6" order="1.0"/>
        <bond id="b6" atomRefs2="C5 H7" order="1.0"/>
        <bond id="b7" atomRefs2="C5 C8" order="1.0"/>
        <bond id="b8" atomRefs2="C8 H9" order="1.0"/>
        <bond id="b9" atomRefs2="C8 H10" order="1.0"/>
        <bond id="b10" atomRefs2="O11 O12" order="1.5"/>
      </bondArray>
      <propertyList>
        <property dictRef="me:ZPE">
          <scalar units="kcal/mol">-168612.428968</scalar>
        </property>
        <property dictRef="me:rotConsts">
          <array units="cm-1">0.273266714401 0.0627290630507 0.0560594489672 </array>
        </property>
        <property dictRef="me:symmetryNumber">
          <scalar>1</scalar>
        </property>
        <property dictRef="me:frequenciesScaleFactor">
          <scalar>1.0</scalar>
        </property>
        <property dictRef="me:imFreqs">
          <scalar units="cm-1">46.2659</scalar>
        </property>
        <!--<property dictRef="me:vibFreqs">
  <array units="cm-1">25.3604 50.5288 56.5932 136.6241 224.9171 258.906 378.1135 542.0147 765.5448 888.965 933.624 1064.9061 1092.4226 1187.324 1283.6447 1380.5613 1438.5228 1492.1404 1495.5602 1528.3576 1536.7189 1591.5982 2941.3584 3033.914 3050.0014 3114.5565 3124.8902 3164.8657 3263.2172 </array>
</property>
-->
        <property title="Hessian" dictRef="me:hessian">
          <matrix rows="36" matrixType="squareSymmetricLT" units="Hartree/Bohr2">0.58198262 -0.00263408 0.48837923 0.00504645 0.03537469 0.56400603 -0.25363186 0.10766586 0.03248026 0.27272075 0.10623971 -0.10533545 -0.01805218 -0.11790809 0.11534253 0.03270074 -0.01839948 -0.05620052 -0.03605058 0.01715208 0.05549785 -0.18531445 -0.0961316 -0.09089152 -0.01933223 -0.01527529 -0.01461876 0.19718563 -0.09498973 -0.11716237 -0.06442221 0.01066194 0.00901708 0.00893701 0.10592376 0.12760354 -0.09093861 -0.06547819 -0.11093996 0.00428256 0.00383751 0.00229924 0.10039221 0.06955507 0.11619122 -0.06234129 -0.00011367 0.05396437 -0.00507452 -0.00074672 0.02963032 0.00613081 0.00106626 -0.02438212 0.06109951 -3.939e-05 -0.04872171 -0.0008748 0.00178604 -0.00032961 -0.01550626 0.00509628 -0.00016602 -0.01640152 0.00033781 0.05302351 0.05383241 0.00019592 -0.29877719 0.00061746 -0.00050309 -0.0032446 0.00360075 -0.00010957 -0.0145236 -0.05951295 -0.0023573 0.32485175 -0.07545271 -0.00079923 0.00097595 0.00321766 0.02732162 -0.01097698 -3.979e-05 -0.02249386 0.00976638 -0.00096819 -0.00763835 0.00228294 0.48749544 -0.00312003 -0.17750536 0.03577566 -0.00150446 -0.01610375 0.00624802 0.00114936 -0.01549027 0.00736354 9.258e-05 -0.00091011 0.0005688 -0.00440492 0.47106829 0.00054801 0.03651419 -0.09765429 -0.00083443 -0.00494524 0.00136536 0.00061197 -0.01682404 0.00613111 0.00043469 0.0336158 -0.01093428 -0.00848949 0.00100854 0.55354964 -0.00095596 -0.00022531 0.00093848 0.00019528 -0.00020911 -0.00068636 -0.00013566 -9.739e-05 0.00030718 0.00090089 -0.00049997 -0.00038349 -0.05276869 -0.00032415 0.04690382 0.06125083 -0.00690143 -0.00014847 0.03268296 0.00041562 0.00134251 -0.00055953 -0.00019953 0.00122407 -0.00059653 -0.00019947 -0.00643564 0.00245707 -0.00028108 -0.05108819 -0.00391858 0.00228926 0.0542936 0.0020944 0.00060726 -0.00965093 -0.00054887 -6.608e-05 0.00037387 0.00032047 0.00021817 0.00058659 -8.511e-05 0.0021965 0.00089842 0.04821609 -0.00078559 -0.28931874 -0.04950577 0.00195911 0.31732677 0.00202666 -0.00077944 0.00018853 0.00128082 -0.00073971 2.661e-05 0.0005949 0.00051104 1.018e-05 0.00020527 0.00012199 -0.00051384 -0.23044923 0.09646556 0.02817593 -0.00713395 0.00394986 0.00269977 0.25875128 0.02952892 -0.01694386 -0.00313691 -0.0008724 -0.00621467 0.00298465 -0.00016541 0.00119346 -0.00088392 -0.00032518 0.00153144 0.00012431 0.08261964 -0.08538608 -0.01120657 0.00132029 -9.228e-05 -0.00053519 -0.09758955 0.09893054 -0.01060361 0.00680967 0.00114578 -0.00011487 0.00240054 2.954e-05 0.00031578 -0.00070868 0.00021573 -0.00060452 -0.0005304 0.00035413 0.02056831 -0.00895843 -0.04719216 0.0306608 -0.01405251 -0.00511296 -0.02449746 0.01173473 0.05094736 -0.00479889 -0.00757699 0.00036349 0.00086477 0.00129321 -2.814e-05 0.0007042 0.00022705 -0.00016422 0.00045093 0.00110917 -0.00073228 -0.1314598 -0.07481096 -0.05834453 0.00035708 0.00184222 -0.00225441 -0.02493356 -0.01618721 -0.01657318 0.26358071 -0.02579357 -0.02379833 -0.01382548 -0.00047465 0.00222184 -0.00080546 -0.00044136 -0.00531919 0.00195247 5.538e-05 0.00171707 -0.00092647 -0.06996505 -0.1222042 -0.02726097 -3.325e-05 0.00197887 -0.00081021 -0.00045922 0.00798546 0.00429301 0.19699338 0.45487628 0.00919993 0.00394389 0.0084993 -9.492e-05 0.00064949 0.00016235 0.00031114 0.00441072 -0.00081178 0.0010968 0.00091715 0.00062658 -0.05820423 -0.03175665 -0.11644922 -0.02679288 -0.01725167 -0.01583009 -0.00522062 0.00144946 0.00026953 0.1362016 -0.13578147 0.5388678 -0.00274923 -0.00010552 -0.00344581 0.00015673 -0.00014293 -5.347e-05 0.00030466 -0.00130072 0.00050835 -0.00011057 0.00018923 8.327e-05 -0.00058245 -0.01783262 0.01183254 0.00067297 0.00069301 -0.0007237 0.00021819 0.00119525 1.342e-05 -0.05793458 -0.09239583 0.02206305 0.05512357 -0.00309792 -0.00055675 -0.00199139 9.7e-05 0.00020344 -1.605e-05 -7.746e-05 -0.00094073 0.00039297 9.063e-05 0.00016373 9.161e-05 -0.00022602 -0.00774396 0.00691166 0.00045177 0.00042786 8.581e-05 -0.00069544 -0.00047826 9.992e-05 -0.09742711 -0.26194666 0.11257695 0.1028772 0.27128562 -0.00237788 -0.00106974 -0.00111952 7.866e-05 4.925e-05 -0.00012755 -0.00021566 -0.00093784 0.00052496 -0.00025436 -0.00026367 0.00035464 -0.00374197 -0.01300826 0.00797619 0.00096668 0.00020857 0.00114661 -0.00059325 -0.00012155 0.00019671 0.02402302 0.10972822 -0.09984136 -0.02675683 -0.11759163 0.09697677 0.00102259 0.00100223 7.276e-05 -1.336e-05 -7.096e-05 0.00011157 -7.264e-05 0.00028128 0.00021492 -0.00020579 -0.00045639 0.00072405 0.00131277 0.0044936 -0.02097458 -0.00262012 -0.00190192 -0.0004667 -0.0008969 0.00016343 0.00071529 -0.0473764 -0.0058759 -0.07692476 0.00528207 -0.00207793 0.00858597 0.04373426 0.00088843 0.00181714 -0.00138035 0.0001917 -0.00026057 -5.726e-05 0.00020213 9.55e-05 0.00023844 -0.00023673 0.0001011 0.00042723 -0.00378429 0.00511928 -0.01396727 -0.00259958 -0.00134121 -0.00279442 -0.00055608 -0.00031364 -0.00098658 -0.00490679 -0.05533234 0.06025667 0.00625057 -0.00039175 0.02340374 0.00435588 0.05063565 0.00057627 0.00129359 0.00075159 7.235e-05 -0.00046406 -5.794e-05 0.00015678 -4.067e-05 0.00032519 -0.00028408 -0.00077484 0.0003681 0.00030064 0.00314035 -0.00749487 -0.00237243 -0.00086655 -0.00050128 -6.056e-05 -0.00014633 -0.00082987 -0.08203698 0.06300461 -0.31379427 -0.00342056 -0.00060354 -0.00607551 0.08720352 -0.06459609 0.32724064 0.00066866 -0.00143468 0.00128638 -0.00050901 0.00095337 -9.7e-06 8.41e-06 0.00085375 -6.68e-05 -0.00016239 -3.567e-05 -0.0001417 0.00311874 -0.00226959 3.578e-05 0.0002973 0.0013455 0.00059051 0.00141446 0.00207886 0.00079645 0.00256866 -0.00546357 -0.00355087 9.857e-05 -0.000468 0.00029143 -1.009e-05 0.00025879 -0.00100189 0.38585834 -0.00012692 0.0001882 -0.0003399 -9.05e-06 -3.297e-05 4.999e-05 -9.902e-05 -0.00016667 3.207e-05 -1.668e-05 3.57e-05 6.188e-05 -0.00126324 0.00077288 0.00014672 -8.298e-05 -0.00033047 -9.08e-05 -0.00047504 -0.00058059 -0.00023998 -0.001008 0.00033079 0.00020828 0.00043999 0.0001086 -0.00039189 0.00021865 -0.00023129 0.00016516 -0.06931558 0.01405308 0.00031169 -0.00076325 0.0008625 -2.99e-06 0.00063444 -0.00014072 5.782e-05 0.00053268 -6.515e-05 -7.506e-05 -8.477e-05 -0.00010783 0.00160014 -0.00117491 1.204e-05 -2.872e-05 0.00103749 0.00062917 0.00061233 0.00121924 0.00062421 0.00123094 -0.003686 -0.00643377 0.00010581 -0.00030825 6.724e-05 0.00158279 -0.00091052 -0.00087055 0.37217557 -0.06512515 0.36891239 -0.00045614 0.00113244 -0.00097934 0.00012496 -0.0007151 -4.524e-05 -3.385e-05 -0.00064338 6.997e-05 7.533e-05 2.924e-05 0.00014338 -0.00342375 0.00206564 0.00010029 -5.996e-05 -0.00105206 -0.00033668 -0.00107793 -0.00176665 -0.0006764 -0.00202313 0.00385365 0.00191576 -0.00047993 0.00055328 -5.8e-06 -0.00015638 -6.403e-05 0.00086693 -0.39335167 0.07173786 -0.37757033 0.40086242 4.602e-05 -0.00021229 0.00018992 -4.953e-05 0.00014963 -2.77e-05 1.814e-05 0.00011158 -1.192e-05 -4.21e-06 -9.47e-06 -3.039e-05 0.00091477 -0.00052853 -7.424e-05 1.042e-05 0.00016933 1.544e-05 0.000246 0.0003685 0.00013872 0.00045204 -0.0005096 0.00037718 0.00013238 -0.00013115 -5.2e-06 -0.00013198 0.00010213 -0.00011163 0.07349682 -0.01414727 0.06862899 -0.07513089 0.01463714 -0.00038979 0.00097142 -0.0009228 0.00011536 -0.00069265 4.311e-05 -4.098e-05 -0.00061062 6.645e-05 7.203e-05 6.411e-05 0.00013387 -0.00229778 0.00157893 9.24e-06 -7.31e-06 -0.00109982 -0.00054743 -0.00082761 -0.00148191 -0.00064801 -0.00168532 0.00411775 0.00473493 -0.00020607 0.00035192 -7.917e-05 -0.00084482 0.00036641 0.00093876 -0.37040517 0.06552364 -0.36348951 0.37651746 -0.06908917 0.35976056 </matrix>
        </property>
        <property dictRef="me:MW">
          <scalar units="amu">75.087</scalar>
        </property>
        <property dictRef="me:spinMultiplicity">
          <scalar>2</scalar>
        </property>
        <property dictRef="me:epsilon">
          <scalar>500.0</scalar>
        </property>
        <property dictRef="me:sigma">
          <scalar>5.0</scalar>
        </property>
      </propertyList>
      <me:energyTransferModel xsi:type="me:ExponentialDown">
        <deltaEDown units="cm-1">400.0</deltaEDown>
      </me:energyTransferModel>
      <me:tmpnode_DOSCMethod name="ClassicalRotors"/>
    </molecule>
    <molecule id="R" description="C3H7 C3H7_45_b3631gd">
      <atomArray>
        <atom id="C1" elementType="C" x3="1.228025" y3="-0.244599" z3="-0.040468"/>
        <atom id="H2" elementType="H" x3="1.301254" y3="-0.764945" z3="-1.001988"/>
        <atom id="H3" elementType="H" x3="1.2837" y3="-1.000757" z3="0.752048"/>
        <atom id="H4" elementType="H" x3="2.101404" y3="0.409563" z3="0.059652"/>
        <atom id="C5" elementType="C" x3="-0.0802" y3="0.55407" z3="0.055066"/>
        <atom id="H6" elementType="H" x3="-0.078374" y3="1.118455" z3="1.007391"/>
        <atom id="H7" elementType="H" x3="-0.104051" y3="1.325099" z3="-0.728721"/>
        <atom id="C8" elementType="C" x3="-1.304629" y3="-0.293929" z3="-0.033557"/>
        <atom id="H9" elementType="H" x3="-1.302278" y3="-1.310629" z3="0.350068"/>
        <atom id="H10" elementType="H" x3="-2.260838" y3="0.129959" z3="-0.324698"/>
      </atomArray>
      <bondArray>
        <bond id="b1" atomRefs2="C1 H2" order="1.0"/>
        <bond id="b2" atomRefs2="C1 H3" order="1.0"/>
        <bond id="b3" atomRefs2="C1 H4" order="1.0"/>
        <bond id="b4" atomRefs2="C1 C5" order="1.0"/>
        <bond id="b5" atomRefs2="C5 H6" order="1.0"/>
        <bond id="b6" atomRefs2="C5 H7" order="1.0"/>
        <bond id="b7" atomRefs2="C5 C8" order="1.0"/>
        <bond id="b8" atomRefs2="C8 H9" order="1.0"/>
        <bond id="b9" atomRefs2="C8 H10" order="1.0"/>
      </bondArray>
      <propertyList>
        <property dictRef="me:ZPE">
          <scalar units="kcal/mol">-74286.2847788</scalar>
        </property>
        <property dictRef="me:rotConsts">
          <array units="cm-1">1.09279767138 0.297276991538 0.258278011784 </array>
        </property>
        <property dictRef="me:symmetryNumber">
          <scalar>1</scalar>
        </property>
        <property dictRef="me:frequenciesScaleFactor">
          <scalar>1.0</scalar>
        </property>
        <!--<property dictRef="me:vibFreqs">
  <array units="cm-1">121.7531 252.1989 368.6367 464.8618 761.1924 890.1136 930.0672 1064.3147 1092.6768 1186.8995 1284.1897 1378.5613 1435.9134 1490.0593 1499.9626 1527.8813 1535.5095 2937.6365 3033.7604 3046.8596 3111.7998 3119.1777 3160.591 3258.0873 </array>
</property>
-->
        <property title="Hessian" dictRef="me:hessian">
          <matrix rows="30" matrixType="squareSymmetricLT" units="Hartree/Bohr2">0.54099177 0.04722545 0.51049429 -0.01104552 0.01967031 0.57684942 -0.0726516 -0.03321355 0.06703506 0.07526602 -0.03273263 -0.09401812 0.09242007 0.03273199 0.10076146 0.06662083 0.0932067 -0.24662179 -0.07284041 -0.10406779 0.26542707 -0.29239428 -0.06270436 -0.01813508 -0.00842646 -0.00234413 -0.00067537 0.31912109 -0.06351981 -0.06479709 -0.00527123 -0.01268849 -0.00397902 -0.00217918 0.06645846 0.069084 -0.01800138 -0.00504646 -0.051874 0.02904511 0.00692779 0.00359055 0.0214324 0.00443582 0.05018846 -0.05217407 -0.01892044 -0.01923999 0.00039547 0.00773552 0.00741497 -0.00174886 -0.02186591 -0.02471239 0.05237555 -0.01837942 -0.16947977 -0.12922616 0.00229395 0.0110647 0.0102397 -0.00086865 -0.00550317 -0.0052394 0.01773886 0.18398507 -0.01911359 -0.13049364 -0.19093701 -0.00405014 -0.0196588 -0.01966182 -0.00028596 -5.219e-05 -0.00137221 0.02212999 0.14262186 0.20383741 -0.11520788 0.0467852 -0.01589552 0.00558292 -0.00818331 0.00109276 -0.01833774 0.02915896 -0.00772096 0.00187584 -0.00446867 0.0013012 0.5488916 0.04619744 -0.15107834 0.01843969 0.00885189 -0.0124591 0.00245923 -0.00382583 0.00672268 -0.00175257 0.01345694 -0.01777489 0.0072194 0.02617465 0.4699655 -0.01607425 0.02227789 -0.08118193 -0.01754433 0.02330344 -0.00447312 -0.00125117 0.00179653 -0.00134426 0.01436918 -0.01983252 0.00642528 0.00854763 0.00300244 0.48829427 0.00447182 0.00928881 -0.0175985 -0.00144023 0.00353691 -0.00115153 0.00081697 -0.00075821 -0.00025318 0.00058895 -0.00092559 0.00042031 -0.06428351 -0.02530455 0.0560756 0.06849577 -0.0068322 -0.01264468 0.02623138 0.00413437 -0.00439603 0.00096136 -1.591e-05 0.0012844 -0.00060321 -0.00100971 0.00081462 -0.0003925 -0.0221623 -0.07201681 0.06760843 0.02419576 0.0852178 0.00203466 0.00370021 -0.0060186 -0.00106016 0.00094848 0.00093082 -0.00034105 -0.00037649 -7.94e-06 -5.723e-05 0.00028258 0.00069395 0.05981061 0.08294548 -0.22622553 -0.06408848 -0.08111258 0.25488339 -0.01696221 -0.00372598 -0.00106059 0.00094633 -0.00015142 -0.00046074 -0.00041851 0.00364821 -0.00078068 0.0004131 0.00018019 0.00054376 -0.27988255 -0.06088907 -0.02081899 -0.01091454 -0.00337139 0.00077577 0.30619689 0.02864599 0.00723232 0.00210921 -0.00085323 0.0011591 -0.00011612 0.00375396 -0.00470359 0.00144752 -0.00063213 0.00108917 -0.0004033 -0.06358853 -0.06782754 -0.00528912 -0.01248504 -0.00297951 0.00042595 0.06712116 0.07298655 -0.00679674 -0.00188698 -0.00119621 -0.00031285 -0.00054069 -7.294e-05 -0.00103193 0.00106635 0.000495 0.00055695 -4.72e-05 0.00016232 -0.02153238 -0.00509543 -0.04648455 0.02947375 0.00846355 0.00177735 0.02412503 0.00867768 0.05424841 0.00239195 0.01530534 0.01609048 0.00042775 -0.0002262 -4.804e-05 0.00072795 0.00046786 0.00113037 -0.00226787 0.00475987 -0.0010055 -0.08451014 -0.00111804 -0.02268689 0.00254539 0.0055925 0.00307914 -0.00121054 -0.02227634 -0.02465829 0.5418679 0.00219055 -0.02574164 -0.02065108 -0.00112585 0.00215699 -0.0008769 -0.00125973 0.00171901 -0.00013099 0.00245451 -0.00327437 0.0006302 0.00019017 -0.14688393 -0.08704527 0.00264507 0.00591412 -0.00550396 -0.00161191 -0.0048667 -0.00765413 -0.13992712 0.40143907 0.00438581 -0.00136727 0.00346 -0.0003066 0.0008183 0.00072126 -0.00081036 0.00095754 0.00035989 -0.00138761 0.0019234 0.00029583 -0.02263704 -0.09226697 -0.13458866 -0.00329365 -0.02229378 -0.02497022 -0.00259678 -0.00541602 -0.00731301 0.15745153 0.19565397 0.29803918 0.00081015 0.00071796 0.00010926 -2.383e-05 -0.00035028 5.858e-05 0.00025954 -0.00063258 -4.844e-05 0.00019404 -0.00011337 0.00019281 0.00150222 0.00092015 0.00164734 -0.00057359 -0.00024335 9.929e-05 0.00071942 4.145e-05 -0.00072015 -0.26519594 -0.01729973 -0.13799009 0.27426978 -0.00192935 0.00194133 0.00033698 -3.387e-05 -0.000395 0.00025169 0.00067935 1.825e-05 -8.761e-05 0.00023006 0.0002133 0.00030192 -0.0166538 9.736e-05 -0.0080508 -0.00067338 -0.00052926 -0.00074995 -0.00119532 -0.00275196 -0.00378089 -0.01962011 -0.04539828 -0.03740848 0.02170234 0.0413052 -7.976e-05 0.00111665 0.00097149 0.00014226 -7.753e-05 2.669e-05 0.00087806 -0.00046078 9.919e-05 0.00019257 0.00029283 -4.957e-05 -0.01972269 -0.00102815 -0.00434831 0.00067611 0.00024197 -0.00055388 0.00101492 -0.00210483 -0.00225245 -0.13291332 -0.03663271 -0.10104683 0.14629022 0.03892804 0.10280206 0.00072435 -0.00075843 -0.00025959 -7.636e-05 -1.645e-05 -1.105e-05 0.00040029 -0.00026848 -9.086e-05 0.00034785 -0.00021717 -0.00013288 0.00436925 -0.0044636 -0.00226413 0.00029298 -0.00028776 -0.00025256 0.00111261 0.00027274 0.0008966 -0.19477645 0.15374403 0.00718479 -0.01196178 0.01749407 0.00352162 0.19956726 -0.00086602 -0.0019083 -0.00405916 -9.72e-05 0.00010501 0.0001213 0.00012684 0.00015452 4.91e-05 0.00081231 -0.00113466 0.00022705 0.01274762 -0.00874492 0.00222898 0.00048021 -0.00066465 -0.00055971 -4.46e-06 0.00066217 0.00079775 0.15704225 -0.18506427 -0.0406007 -0.00474259 0.00549906 -0.00027549 -0.16549895 0.19109605 -0.00193006 -0.0011774 -0.00345137 -0.00010794 -7.327e-05 0.00013327 0.00022046 8.362e-05 -0.00013467 0.00073355 -0.00101508 0.00060581 0.01675639 -0.01392313 0.00392681 -0.00026044 0.00089538 -0.00050934 -0.0007417 0.00066903 0.00063609 0.00356052 -0.03778915 -0.03495743 -0.00963882 0.01025911 0.00435163 -0.00859195 0.0420709 0.02939921 </matrix>
        </property>
        <property dictRef="me:MW">
          <scalar units="amu">43.089</scalar>
        </property>
        <property dictRef="me:spinMultiplicity">
          <scalar>2</scalar>
        </property>
        <property dictRef="me:epsilon">
          <scalar>500.0</scalar>
        </property>
        <property dictRef="me:sigma">
          <scalar>5.0</scalar>
        </property>
      </propertyList>
      <me:energyTransferModel xsi:type="me:ExponentialDown">
        <deltaEDown units="cm-1">400.0</deltaEDown>
      </me:energyTransferModel>
      <me:tmpnode_DOSCMethod name="ClassicalRotors"/>
    </molecule>
    <molecule id="O2" description="O2 O2_31_b3631gd">
      <atomArray>
        <atom id="O1" elementType="O" x3="0.0" y3="0.0" z3="0.607296"/>
        <atom id="O2" elementType="O" x3="0.0" y3="0.0" z3="-0.607296"/>
      </atomArray>
      <bondArray>
        <bond id="b1" atomRefs2="O1 O2" order="1.5"/>
      </bondArray>
      <propertyList>
        <property dictRef="me:ZPE">
          <scalar units="kcal/mol">-94324.9581951</scalar>
        </property>
        <property dictRef="me:rotConsts">
          <array units="cm-1">1.42883834656 </array>
        </property>
        <property dictRef="me:symmetryNumber">
          <scalar>2</scalar>
        </property>
        <property dictRef="me:frequenciesScaleFactor">
          <scalar>1.0</scalar>
        </property>
        <!--<property dictRef="me:vibFreqs">
  <array units="cm-1">1658.8545 </array>
</property>
-->
        <property title="Hessian" dictRef="me:hessian">
          <matrix rows="6" matrixType="squareSymmetricLT" units="Hartree/Bohr2">0.83283691 0.0 8.358e-05 0.0 0.0 8.358e-05 -0.83283691 0.0 0.0 0.83283691 0.0 -8.358e-05 0.0 0.0 8.358e-05 0.0 0.0 -8.358e-05 0.0 0.0 8.358e-05 </matrix>
        </property>
        <property dictRef="me:MW">
          <scalar units="amu">31.998</scalar>
        </property>
        <property dictRef="me:spinMultiplicity">
          <scalar>3</scalar>
        </property>
        <property dictRef="me:epsilon">
          <scalar>500.0</scalar>
        </property>
        <property dictRef="me:sigma">
          <scalar>5.0</scalar>
        </property>
      </propertyList>
      <me:energyTransferModel xsi:type="me:ExponentialDown">
        <deltaEDown units="cm-1">400.0</deltaEDown>
      </me:energyTransferModel>
      <me:tmpnode_DOSCMethod name="ClassicalRotors"/>
    </molecule>
    <molecule id="He">
      <atomArray>
        <atom id="He1" elementType="He"/>
      </atomArray>
      <propertyList>
        <property dictRef="me:epsilon">
          <scalar>10.2</scalar>
        </property>
        <property dictRef="me:sigma">
          <scalar>2.55</scalar>
        </property>
        <property dictRef="me:MW">
          <scalar units="amu">4.0026</scalar>
        </property>
      </propertyList>
    </molecule>
  </moleculeList>
  <reactionList>
    <reaction id="R1">
      <reactant>
        <molecule ref="RO2" role="modelled"/>
      </reactant>
      <product>
        <molecule ref="R" role="sink"/>
      </product>
      <product>
        <molecule ref="O2" role="sink"/>
      </product>
      <me:transitionState>
        <molecule ref="TS_286" role="transitionState"/>
      </me:transitionState>
      <me:MCRCMethod name="SimpleRRKM"/>
      <me:tunneling name="Eckart"/>
    </reaction>
  </reactionList>
  <me:conditions>
    <me:bathGas>He</me:bathGas>
    <me:PTs>
      <me:PTpair units="atm" P="20" T="298.15"/>
      <me:PTpair units="atm" P="20" T="300.0"/>
      <me:PTpair units="atm" P="20" T="400.0"/>
      <me:PTpair units="atm" P="20" T="450.0"/>
      <me:PTpair units="atm" P="20" T="500.0"/>
      <me:PTpair units="atm" P="20" T="550.0"/>
      <me:PTpair units="atm" P="20" T="600.0"/>
      <me:PTpair units="atm" P="20" T="650.0"/>
      <me:PTpair units="atm" P="20" T="700.0"/>
      <me:PTpair units="atm" P="20" T="750.0"/>
      <me:PTpair units="atm" P="20" T="800.0"/>
      <me:PTpair units="atm" P="20" T="850.0"/>
      <me:PTpair units="atm" P="20" T="900.0"/>
    </me:PTs>
  </me:conditions>
  <me:modelParameters>
    <me:grainSize units="cm-1">25.0</me:grainSize>
    <me:energyAboveTheTopHill>200.0</me:energyAboveTheTopHill>
  </me:modelParameters>
  <me:control>
    <me:testMicroRates/>
    <me:testRateConstants/>
  </me:control>
</me:mesmer>
